{
    "title": "Docker Basic Command",
    "description": "learn how to pull images , run containers and list containers ",
    "difficulty": "Beginner",
    "time": "20",
    "details": {
      "steps": [
        {
          "title": "Pull Image",
          "text": "step1-pull.md"
        },
        {
          "title": "Run Container",
          "text": "step2-run.md"
        },
        {
          "title": "List Containers",
          "text": "step1-list.md"
        }
      ],
      "intro": {
        "text": "intro.md"
      },
      "finish": {
        "text": "finish.md"
      }
    },
    "environment": {
      "uilayout": "terminal"
    },
    "backend": {
      "imageid": "ubuntu:2004"
    }
  }